RawForge/__init__.py
RawForge/main.py
RawForge/application/InferenceWorker.py
RawForge/application/MODEL_REGISTRY.py
RawForge/application/ModelHandler.py
RawForge/application/dng_utils.py
RawForge/application/postprocessing.py
RawForge/application/utils.py
rawforge-0.0.1.dist-info/licenses/LICENSE
rawforge-0.0.1.dist-info/METADATA
rawforge-0.0.1.dist-info/WHEEL
rawforge-0.0.1.dist-info/entry_points.txt
rawforge-0.0.1.dist-info/top_level.txt
rawforge-0.0.1.dist-info/RECORD
