Metadata-Version: 2.4
Name: rawforge
Version: 0.0.1
Summary: A compute backend/CLI application for using machine learning models on raw images.
Author: Ryan Mueller
License: MIT License
Project-URL: Homepage, https://github.com/rymuelle/RawForge
Project-URL: Bug Tracker, https://github.com/rymuelle/RawForge/issues
Keywords: python,Machine Learning,Camera Raw
Classifier: Programming Language :: Python :: 3
Classifier: Programming Language :: Python :: 3.11
Classifier: Programming Language :: Python :: 3.12
Classifier: Programming Language :: Python :: 3.13
Classifier: License :: OSI Approved :: MIT License
Classifier: Operating System :: OS Independent
Requires-Python: >=3.11
License-File: LICENSE
Requires-Dist: pidng~=4.0.9
Requires-Dist: numpy>=2.3
Requires-Dist: RawHandler~=0.0.2
Requires-Dist: colour_demosaicing~=0.2.6
Requires-Dist: blended_tiling>=0.0.1.dev7
Requires-Dist: requests~=2.32
Requires-Dist: platformdirs~=4.5
Requires-Dist: tqdm~=4.67
Requires-Dist: cryptography~=46.0
Dynamic: license-file
